skype_client/__init__.py
skype_client/skype_utils.py
skype_client-1.0.0.dist-info/METADATA
skype_client-1.0.0.dist-info/WHEEL
skype_client-1.0.0.dist-info/licenses/LICENSE
skype_client-1.0.0.dist-info/RECORD
